{
    "updated_at": "2026-04-02T09:10:01.946523+00:00",
    "symbol": "BTCUSDT",
    "signal_context": {
        "summary": "Актуальных новостей: 30. Подтверждённых событий: 0."
    },
    "features": {
        "confirmed_events_count": 0,
        "risk_off_pressure": 0.6667,
        "avg_confirmed_btc_relevance": 0,
        "oil_shock_count": 6
    },
    "items": [
        {
            "published_at": "2026-04-02T08:56:29+00:00",
            "source": "fxstreet",
            "title": "ECB's Panetta: Tensions in energy markets are a cause for concern for financial stability",
            "url": "https://www.fxstreet.com/news/ecbs-panetta-tensions-in-energy-markets-are-a-cause-for-concern-for-financial-stability-202604020856",
            "summary": "European Central Bank (ECB) executive board member Fabio Panetta said during European trading hours on Thursday that global energy crisis could impact financial stability.",
            "sentiment": -0.2,
            "impact_score": 0.6,
            "requires_confirmation": true,
            "is_confirmed": false,
            "source_layer": "global_primary",
            "btc_relevance_score": 0.75,
            "event_key": "macro_eu_rates",
            "market_regime_effect": "macro_uncertainty"
        },
        {
            "published_at": "2026-04-02T08:44:56+00:00",
            "source": "fxstreet",
            "title": "USD: Risk-off tone supports Dollar – ING",
            "url": "https://www.fxstreet.com/news/usd-risk-off-tone-supports-dollar-ing-202604020844",
            "summary": "ING analysts Francesco Pesole, Frantisek Taborsky and Chris Turner note that the US Dollar has regained support as risk-off sentiment returns following renewed Middle East escalation and uncertainty around the Strait of Hormuz.",
            "sentiment": -0.4,
            "impact_score": 0.7,
            "requires_confirmation": true,
            "is_confirmed": false,
            "source_layer": "global_primary",
            "btc_relevance_score": 0.85,
            "event_key": "macro_us_shipping",
            "market_regime_effect": "risk_off"
        },
        {
            "published_at": "2026-04-02T08:41:19+00:00",
            "source": "fxstreet",
            "title": "US Dollar Index (DXY) rallies beyond 100.00 as hopes of peace in Iran fade",
            "url": "https://www.fxstreet.com/news/us-dollar-index-dxy-rallies-beyond-10000-as-hopes-of-peace-in-iran-fade-202604020841",
            "summary": "The US Dollar (USD) is regaining lost ground on Thursday, and the DXY returns to levels above the 100.00 line at the time of writing, buoyed by the risk-averse sentiment. US President Donald Trump crushed hopes of a swift end to the Iran war and sent the Greenback higher across the board.",
            "sentiment": -0.4,
            "impact_score": 0.7,
            "requires_confirmation": true,
            "is_confirmed": false,
            "source_layer": "global_primary",
            "btc_relevance_score": 0.85,
            "event_key": "macro_iran_usd",
            "market_regime_effect": "macro_uncertainty"
        },
        {
            "published_at": "2026-04-02T08:36:07+00:00",
            "source": "fxstreet",
            "title": "WTI rises above 101.00 as Trump’s Iran stance fuels supply fears",
            "url": "https://www.fxstreet.com/news/wti-rises-above-10100-as-trumps-iran-stance-fuels-supply-fears-202604020836",
            "summary": "West Texas Intermediate (WTI) oil price rises over 7% after two days of losses, trading around $101.10 per barrel during the European hours on Thursday.",
            "sentiment": -0.2,
            "impact_score": 0.6,
            "requires_confirmation": true,
            "is_confirmed": false,
            "source_layer": "global_primary",
            "btc_relevance_score": 0.85,
            "event_key": "geopolitics_iran_oil",
            "market_regime_effect": "risk_off"
        },
        {
            "published_at": "2026-04-02T08:19:16+00:00",
            "source": "fxstreet",
            "title": "Oil: War risks and Strait tensions – Rabobank",
            "url": "https://www.fxstreet.com/news/oil-war-risks-and-strait-tensions-rabobank-202604020819",
            "summary": "Rabobank’s Senior Market Strategist Benjamin Picton notes that Brent briefly fell below $100 before Donald Trump’s national address reversed risk sentiment, sending Oil higher and bond yields up.",
            "sentiment": -0.6,
            "impact_score": 0.7,
            "requires_confirmation": true,
            "is_confirmed": false,
            "source_layer": "global_primary",
            "btc_relevance_score": 0.85,
            "event_key": "macro_us_oil",
            "market_regime_effect": "risk_off"
        },
        {
            "published_at": "2026-04-02T07:53:11+00:00",
            "source": "fxstreet",
            "title": "ECB Simkus: Too early to say what we'll need to do in April",
            "url": "https://www.fxstreet.com/news/ecb-simkus-too-early-to-say-what-well-need-to-do-in-april-202604020753",
            "summary": "European Central Bank (ECB) Governing Council (GC) member and Governor of the Lithuanian central bank, Gediminas Simkus, said during European trading hours on Thursday that the central bank needs to exercise caution on interest rates as the situation is changing.",
            "sentiment": -0.2,
            "impact_score": 0.6,
            "requires_confirmation": true,
            "is_confirmed": false,
            "source_layer": "global_primary",
            "btc_relevance_score": 0.75,
            "event_key": "macro_eu_rates",
            "market_regime_effect": "macro_uncertainty"
        },
        {
            "published_at": "2026-04-02T07:40:40+00:00",
            "source": "fxstreet",
            "title": "US: Inflation upturn with oil shock – Commerzbank",
            "url": "https://www.fxstreet.com/news/us-inflation-upturn-with-oil-shock-commerzbank-202604020740",
            "summary": "Commerzbank economists Dr. Christoph Balz and Dr. Ralph Solveen argue that higher Oil prices from the Iran War are set to push US inflation higher. They expect March CPI to rise 0.9% month-on-month and 3.3% year-on-year, with core at 0.3% and 2.7%.",
            "sentiment": -0.6,
            "impact_score": 0.7,
            "requires_confirmation": true,
            "is_confirmed": false,
            "source_layer": "global_primary",
            "btc_relevance_score": 0.85,
            "event_key": "macro_iran_oil",
            "market_regime_effect": "risk_off"
        },
        {
            "published_at": "2026-04-02T07:30:31+00:00",
            "source": "fxstreet",
            "title": "NZD/USD Price Forecast: Holds losses near 0.5700, four-month lows",
            "url": "https://www.fxstreet.com/news/nzd-usd-price-forecast-holds-losses-near-05700-four-month-lows-202604020730",
            "summary": "NZD/USD depreciates nearly 0.8% after two days of gains, trading around 0.5710 during the European hours on Thursday. The technical analysis of the daily chart signals a persistent bearish bias as the pair remains within a descending channel pattern.",
            "sentiment": 0.0,
            "impact_score": 0.65,
            "requires_confirmation": true,
            "is_confirmed": false,
            "source_layer": "global_primary",
            "btc_relevance_score": 0.75,
            "event_key": "macro_eu_usd",
            "market_regime_effect": "macro_uncertainty"
        },
        {
            "published_at": "2026-04-02T07:22:32+00:00",
            "source": "fxstreet",
            "title": "Forex Today: US Dollar rebounds as mood sours after Trump remarks",
            "url": "https://www.fxstreet.com/news/forex-today-us-dollar-rebounds-as-mood-sours-after-trump-remarks-202604020722",
            "summary": "Here is what you need to know on Thursday, April 2:",
            "sentiment": 0.0,
            "impact_score": 0.55,
            "requires_confirmation": true,
            "is_confirmed": false,
            "source_layer": "global_primary",
            "btc_relevance_score": 0.85,
            "event_key": "macro_us_usd",
            "market_regime_effect": "macro_uncertainty"
        },
        {
            "published_at": "2026-04-02T03:54:05+00:00",
            "source": "fxstreet",
            "title": "Canadian Dollar declines as Trump remarks lift US Dollar",
            "url": "https://www.fxstreet.com/news/canadian-dollar-declines-as-trump-remarks-lift-us-dollar-202604020354",
            "summary": "USD/CAD rebounds after two days of losses, trading around 1.3900 during the Asian hours on Thursday. The pair appreciates as the US Dollar (USD) strengthens after US President Donald Trump’s latest address showed no clear Middle East de-escalation, keeping geopolitical risk elevated.",
            "sentiment": -0.6,
            "impact_score": 0.7,
            "requires_confirmation": true,
            "is_confirmed": false,
            "source_layer": "global_primary",
            "btc_relevance_score": 0.85,
            "event_key": "macro_us_usd",
            "market_regime_effect": "macro_uncertainty"
        },
        {
            "published_at": "2026-04-02T02:42:27+00:00",
            "source": "fxstreet",
            "title": "NZD/USD declines below 0.5750 as Iran conflict supports US Dollar",
            "url": "https://www.fxstreet.com/news/nzd-usd-declines-below-05750-as-iran-conflict-supports-us-dollar-202604020242",
            "summary": "The NZD/USD pair tumbles to near 0.5725 during the Asian trading hours on Thursday. The US Dollar (USD) edges higher against the New Zealand Dollar (NZD) as market caution persists due to the ongoing conflict in the Middle East, which boosts safe-haven demand.",
            "sentiment": -0.4,
            "impact_score": 0.7,
            "requires_confirmation": true,
            "is_confirmed": false,
            "source_layer": "global_primary",
            "btc_relevance_score": 0.85,
            "event_key": "macro_iran_usd",
            "market_regime_effect": "macro_uncertainty"
        },
        {
            "published_at": "2026-04-02T01:52:53+00:00",
            "source": "fxstreet",
            "title": "Japanese Yen softens after Trump Iran war remarks",
            "url": "https://www.fxstreet.com/news/japanese-yen-softens-after-trump-iran-war-remarks-202604020152",
            "summary": "The USD/JPY pair gains momentum to near 159.20 during the Asian trading hours on Thursday. The US Dollar (USD) strengthens against the Japanese Yen (JPY) following US President Donald Trump’s speech from the White House.",
            "sentiment": 0.0,
            "impact_score": 0.65,
            "requires_confirmation": true,
            "is_confirmed": false,
            "source_layer": "global_primary",
            "btc_relevance_score": 0.85,
            "event_key": "macro_iran_usd",
            "market_regime_effect": "macro_uncertainty"
        }
    ],
    "legacy_summary": {
        "news_count": 30,
        "avg_sentiment": -0.15,
        "avg_impact_score": 0.635,
        "primary_count": 0,
        "secondary_count": 0,
        "requires_confirmation_count": 30
    }
}