{
    "updated_at": "2026-04-08T21:10:07.246917+00:00",
    "symbol": "BTCUSDT",
    "signal_context": {
        "summary": "Актуальных новостей: 30. Подтверждённых событий: 0."
    },
    "features": {
        "confirmed_events_count": 0,
        "risk_off_pressure": 0.6611,
        "avg_confirmed_btc_relevance": 0,
        "oil_shock_count": 6
    },
    "items": [
        {
            "published_at": "2026-04-08T19:52:57+00:00",
            "source": "fxstreet",
            "title": "NZD/USD Price Forecast: Rallies above 0.5800, eyes on 200-day SMA",
            "url": "https://www.fxstreet.com/news/nzd-usd-price-forecast-rallies-above-05800-eyes-on-200-day-sma-202604081952",
            "summary": "The NZD/USD rallied sharply on Wednesday, boosted by a double whammy. The de-escalation of the Middle East conflict, and hawkish remarks by the RBNZ Governor, Anna Breman, post the bank’s monetary policy meeting.",
            "sentiment": -0.6,
            "impact_score": 0.7,
            "requires_confirmation": true,
            "is_confirmed": false,
            "source_layer": "global_primary",
            "btc_relevance_score": 0.75,
            "event_key": "macro_none_usd",
            "market_regime_effect": "macro_uncertainty"
        },
        {
            "published_at": "2026-04-08T19:49:00+00:00",
            "source": "fxstreet",
            "title": "Singapore: Energy buffers seen limiting near‑term risks – MUFG",
            "url": "https://www.fxstreet.com/news/singapore-energy-buffers-seen-limiting-near-term-risks-mufg-202604081949",
            "summary": "MUFG’s Senior Currency Analyst Lloyd Chan argues Singapore’s energy system and fiscal strength materially limit near‑term tail risks from Middle East tensions.",
            "sentiment": -0.2,
            "impact_score": 0.4,
            "requires_confirmation": true,
            "is_confirmed": false,
            "source_layer": "global_primary",
            "btc_relevance_score": 0.35,
            "event_key": "general_none_none",
            "market_regime_effect": "neutral"
        },
        {
            "published_at": "2026-04-08T19:14:58+00:00",
            "source": "fxstreet",
            "title": "Forex Today: FOMC Minutes reinforce 'higher-for-longer' as markets digest the ceasefire",
            "url": "https://www.fxstreet.com/news/forex-today-fomc-minutes-reinforce-higher-for-longer-as-markets-digest-the-ceasefire-202604081914",
            "summary": "The US Dollar Index (DXY) holds firm near 99.10, supported by safe-haven demand late in the American session with expectations that the Federal Reserve (Fed) will remain cautious on easing.",
            "sentiment": 0.2,
            "impact_score": 0.6,
            "requires_confirmation": true,
            "is_confirmed": false,
            "source_layer": "global_primary",
            "btc_relevance_score": 0.85,
            "event_key": "macro_fed_rates",
            "market_regime_effect": "macro_uncertainty"
        },
        {
            "published_at": "2026-04-08T19:07:00+00:00",
            "source": "fxstreet",
            "title": "US: Demand still dominant but moderating – BNP Paribas",
            "url": "https://www.fxstreet.com/news/us-demand-still-dominant-but-moderating-bnp-paribas-202604081907",
            "summary": "BNP Paribas analysts assess that in the United States (USD), demand remains the main driver of inflation, though its contribution has eased from post‑Covid peaks.",
            "sentiment": 0.2,
            "impact_score": 0.6,
            "requires_confirmation": true,
            "is_confirmed": false,
            "source_layer": "global_primary",
            "btc_relevance_score": 0.85,
            "event_key": "macro_us_usd",
            "market_regime_effect": "macro_uncertainty"
        },
        {
            "published_at": "2026-04-08T19:00:31+00:00",
            "source": "fxstreet",
            "title": "DXY bounces from fresh lows as ceasefire cracks widen on all sides",
            "url": "https://www.fxstreet.com/news/dxy-bounces-from-fresh-lows-as-ceasefire-cracks-widen-on-all-sides-202604081900",
            "summary": "The US Dollar Index (DXY) continued to grind lower during the front half of the US trading session on Wednesday, falling roughly 1% from the prior session's close near 100.00 to tag a low around 98.50 as the US-Iran ceasefire announcement triggered a broad wave of risk-on selling in the US Dollar.",
            "sentiment": 0.0,
            "impact_score": 0.65,
            "requires_confirmation": true,
            "is_confirmed": false,
            "source_layer": "global_primary",
            "btc_relevance_score": 0.85,
            "event_key": "macro_iran_usd",
            "market_regime_effect": "macro_uncertainty"
        },
        {
            "published_at": "2026-04-08T16:40:52+00:00",
            "source": "fxstreet",
            "title": "Hungary: Inflation set to reaccelerate – ING",
            "url": "https://www.fxstreet.com/news/hungary-inflation-set-to-reaccelerate-ing-202604081640",
            "summary": "ING economists Peter Virovacz and Zoltán Homolya note that Hungarian inflation in March 2026 surprised on the downside versus expectations but remained above February’s decade low.",
            "sentiment": 0.0,
            "impact_score": 0.55,
            "requires_confirmation": true,
            "is_confirmed": false,
            "source_layer": "global_primary",
            "btc_relevance_score": 0.85,
            "event_key": "macro_us_inflation",
            "market_regime_effect": "macro_uncertainty"
        },
        {
            "published_at": "2026-04-08T16:31:02+00:00",
            "source": "fxstreet",
            "title": "WTI slides sharply after US-Iran ceasefire removes war premium",
            "url": "https://www.fxstreet.com/news/wti-slides-sharply-after-us-iran-ceasefire-removes-war-premium-202604081631",
            "summary": "West Texas Intermediate (WTI) Crude Oil trades sharply lower on Wednesday, falling more than 10% after a temporary ceasefire agreement between the United States and Iran reduced the geopolitical risk premium embedded in prices.",
            "sentiment": -0.4,
            "impact_score": 0.7,
            "requires_confirmation": true,
            "is_confirmed": false,
            "source_layer": "global_primary",
            "btc_relevance_score": 0.85,
            "event_key": "geopolitics_iran_oil",
            "market_regime_effect": "risk_off"
        },
        {
            "published_at": "2026-04-08T16:15:00+00:00",
            "source": "fxstreet",
            "title": "Fed Minutes to offer insights into March hold decision amid hawkish outlook",
            "url": "https://www.fxstreet.com/news/fed-minutes-to-offer-insights-into-march-hold-decision-amid-hawkish-outlook-202604081315",
            "summary": "The Federal Reserve (Fed) will publish its Minutes from the March 18 meeting on Wednesday. The release should be less about the decision itself and more about the officials’ “no rush to cut” narrative.",
            "sentiment": 0.2,
            "impact_score": 0.6,
            "requires_confirmation": true,
            "is_confirmed": false,
            "source_layer": "global_primary",
            "btc_relevance_score": 0.85,
            "event_key": "macro_fed_rates",
            "market_regime_effect": "macro_uncertainty"
        },
        {
            "published_at": "2026-04-08T15:00:45+00:00",
            "source": "fxstreet",
            "title": "Brent: Elevated prices after ceasefire relief – Commerzbank",
            "url": "https://www.fxstreet.com/news/brent-elevated-prices-after-ceasefire-relief-commerzbank-202604081500",
            "summary": "Commerzbank’s Thu Lan Nguyen notes that Brent prices dropped by USD 15 on news of a two‑week U.S.–Iran ceasefire and reopening of the Strait of Hormuz, but still trade near USD 95, well above pre‑war levels.",
            "sentiment": -0.6,
            "impact_score": 0.7,
            "requires_confirmation": true,
            "is_confirmed": false,
            "source_layer": "global_primary",
            "btc_relevance_score": 0.85,
            "event_key": "macro_iran_oil",
            "market_regime_effect": "risk_off"
        },
        {
            "published_at": "2026-04-08T14:58:32+00:00",
            "source": "fxstreet",
            "title": "Oil tankers passing through Hormuz stopped after Israel's ceasefire breach – Fars News Agency",
            "url": "https://www.fxstreet.com/news/oil-tankers-passing-through-hormuz-stopped-after-israels-ceasefire-breach-fars-news-agency-202604081458",
            "summary": "Iran's Fars News Agency reported on Wednesday that oil tankers passing through the Strait of Hormuz have been stopped after Israel breached the ceasefire, per Reuters.",
            "sentiment": 0.2,
            "impact_score": 0.6,
            "requires_confirmation": true,
            "is_confirmed": false,
            "source_layer": "global_primary",
            "btc_relevance_score": 0.75,
            "event_key": "geopolitics_israel_oil",
            "market_regime_effect": "risk_off"
        },
        {
            "published_at": "2026-04-08T14:49:38+00:00",
            "source": "fxstreet",
            "title": "Eurozone: Weak demand offsets supply constraints – BNP Paribas",
            "url": "https://www.fxstreet.com/news/eurozone-weak-demand-offsets-supply-constraints-bnp-paribas-202604081449",
            "summary": "BNP Paribas analysts argue that weaker demand in the Eurozone compared to 2022 is helping to contain inflation, even as supply constraints remain above historical averages.",
            "sentiment": 0.0,
            "impact_score": 0.55,
            "requires_confirmation": true,
            "is_confirmed": false,
            "source_layer": "global_primary",
            "btc_relevance_score": 0.75,
            "event_key": "macro_eu_inflation",
            "market_regime_effect": "macro_uncertainty"
        },
        {
            "published_at": "2026-04-08T12:06:50+00:00",
            "source": "fxstreet",
            "title": "Oil: Prices slump below $100 on ceasefire – ING",
            "url": "https://www.fxstreet.com/news/oil-prices-slump-below-100-on-ceasefire-ing-202604081206",
            "summary": "ING’s commodities team of Ewa Manthey and Warren Patterson report that Oil prices have dropped sharply, with Brent and WTI falling well below $100 as a US–Iran two‑week ceasefire eases supply disruption fears.",
            "sentiment": -0.6,
            "impact_score": 0.7,
            "requires_confirmation": true,
            "is_confirmed": false,
            "source_layer": "global_primary",
            "btc_relevance_score": 0.85,
            "event_key": "geopolitics_iran_oil",
            "market_regime_effect": "risk_off"
        }
    ],
    "legacy_summary": {
        "news_count": 30,
        "avg_sentiment": -0.04,
        "avg_impact_score": 0.6383,
        "primary_count": 0,
        "secondary_count": 0,
        "requires_confirmation_count": 30
    }
}